slope/__init__.py
slope-0.1.0.dist-info/LICENSE
slope-0.1.0.dist-info/METADATA
slope-0.1.0.dist-info/WHEEL
slope-0.1.0.dist-info/top_level.txt
slope-0.1.0.dist-info/RECORD
