Metadata-Version: 2.1
Name: slope
Version: 0.1.0
Summary: An easy-to-use coreference resolution library.
Home-page: https://github.com/ryanelliott10/slope
Author: Ryan Elliott
Author-email: ryelliot@calpoly.edu
License: MIT
Platform: UNKNOWN
Classifier: License :: OSI Approved :: MIT License
Classifier: Programming Language :: Python
Classifier: Programming Language :: Python :: 3
Classifier: Programming Language :: Python :: 3.6
Classifier: Programming Language :: Python :: Implementation :: CPython
Classifier: Programming Language :: Python :: Implementation :: PyPy
Requires-Python: >=3.6.0
Requires-Dist: spacy
